rtl/alu.v
module alu(
    input wire [31:0] operand1,
    input wire [31:0] operand2,
    input wire [3:0] alu_control,
    output reg [31:0] result,
    output wire zero
);

    // Lógica combinacional para las operaciones de la ALU
    always @(*) begin
        case (alu_control)
            4'b0000: result = operand1 & operand2; // AND
            4'b0001: result = operand1 | operand2; // OR
            4'b0010: result = operand1 + operand2; // ADD
            4'b0011: result = operand1 << operand2[4:0]; // SLL
            4'b0100: result = operand1 >> operand2[4:0]; // SRL
            4'b0101: result = $signed(operand1) >>> operand2[4:0]; // SRA
            4'b0110: result = operand1 - operand2; // SUB
            4'b0111: result = ($signed(operand1) < $signed(operand2)) ? 32'd1 : 32'd0; // SLT
            4'b1000: result = (operand1 < operand2) ? 32'd1 : 32'd0; // SLTU
            4'b1001: result = operand1 ^ operand2; // XOR
            default: result = 32'hxxxxxxxx; // Valor por defecto
        endcase
    end

    // La bandera 'zero' se activa si el resultado es 0
    assign zero = (result == 32'b0);

endmodule

tb/tb_alu.v
`timescale 1ns / 1ps

module tb_alu;

    // --- Testbench内部信号 ---
    reg  [31:0] tb_operand1;
    reg  [31:0] tb_operand2;
    reg  [3:0]  tb_alu_control;

    wire [31:0] tb_result;
    wire        tb_zero;

    integer tests_passed = 0;
    integer tests_failed = 0;

    // --- 实例化待测模块 (DUT: Design Under Test) ---
    alu uut (
        .operand1(tb_operand1),
        .operand2(tb_operand2),
        .alu_control(tb_alu_control),
        .result(tb_result),
        .zero(tb_zero)
    );

    // --- ALU操作码定义 (与您的alu.v和control_unit.v保持一致) ---
    localparam ALU_AND  = 4'b0000;
    localparam ALU_OR   = 4'b0001;
    localparam ALU_ADD  = 4'b0010;
    localparam ALU_SLL  = 4'b0011;
    localparam ALU_SRL  = 4'b0100;
    localparam ALU_SRA  = 4'b0101;
    localparam ALU_SUB  = 4'b0110;
    localparam ALU_SLT  = 4'b0111;
    localparam ALU_SLTU = 4'b1000;
    localparam ALU_XOR  = 4'b1001;

    // --- 自动化检查任务 ---
    task check_alu;
        input [31:0] op1, op2;
        input [3:0]  ctrl;
        input [31:0] expected_result;
        input        expected_zero;
        input [255:0] test_name;
        begin
            // 1. 应用激励
            tb_operand1 = op1;
            tb_operand2 = op2;
            tb_alu_control = ctrl;
            
            #1; // 等待1ns，让组合逻辑传播和稳定

            // 2. 检查结果
            if (tb_result === expected_result && tb_zero === expected_zero) begin
                $display("PASS: %s", test_name);
                tests_passed = tests_passed + 1;
            end else begin
                $display("FAIL: %s", test_name);
                $display("      Inputs: op1=%h, op2=%h, ctrl=%b", op1, op2, ctrl);
                $display("      Result -> Expected: %h, Got: %h", expected_result, tb_result);
                $display("      Zero   -> Expected: %b, Got: %b", expected_zero, tb_zero);
                tests_failed = tests_failed + 1;
            end
        end
    endtask

    // --- 主要测试序列 ---
    initial begin
        $dumpfile("alu_waves.vcd"); // 设置输出的波形文件名
        $dumpvars(0, tb_alu);       // 指示仿真器记录tb_alu模块下所有信号的变化
        $display("--- Starting ALU Testbench ---");

        // --- ADD Tests ---
        check_alu(10, 20, ALU_ADD, 30, 0, "ADD: 10 + 20");
        check_alu(32'hFFFFFFFF, 1, ALU_ADD, 0, 1, "ADD: -1 + 1 (tests zero flag)");
        
        // --- SUB Tests ---
        check_alu(10, 20, ALU_SUB, -10, 0, "SUB: 10 - 20");
        check_alu(50, 50, ALU_SUB, 0, 1, "SUB: 50 - 50 (tests zero flag)");
        
        // --- Logical Tests ---
        check_alu(32'hF0F0F0F0, 32'h0F0F0F0F, ALU_AND, 32'h00000000, 1, "AND");
        check_alu(32'hF0F0F0F0, 32'h0F0F0F0F, ALU_OR,  32'hFFFFFFFF, 0, "OR");
        check_alu(32'hF0F0F0F0, 32'h0F0F0F0F, ALU_XOR, 32'hFFFFFFFF, 0, "XOR");

        // --- Shift Tests ---
        check_alu(32'h0000000A, 2, ALU_SLL, 32'h00000028, 0, "SLL: 10 << 2");
        check_alu(32'hFFFFFFF6, 2, ALU_SRL, 32'h3FFFFFFD, 0, "SRL: -10 >> 2 (logical)");
        check_alu(32'hFFFFFFF6, 2, ALU_SRA, 32'hFFFFFFFD, 0, "SRA: -10 >>> 2 (arithmetic)");

        // --- Comparison Tests (SLT - Signed) ---
        check_alu(10, 20, ALU_SLT, 1, 0, "SLT: 10 < 20 (signed)");
        check_alu(20, 10, ALU_SLT, 0, 1, "SLT: 20 < 10 (signed)");
        check_alu(-10, 10, ALU_SLT, 1, 0, "SLT: -10 < 10 (signed)");
        check_alu(10, -10, ALU_SLT, 0, 1, "SLT: 10 < -10 (signed)");

        // --- Comparison Tests (SLTU - Unsigned) ---
        check_alu(10, 20, ALU_SLTU, 1, 0, "SLTU: 10 < 20 (unsigned)");
        check_alu(20, 10, ALU_SLTU, 0, 1, "SLTU: 20 < 10 (unsigned)");
        // Crucial test: -10 is a very large positive number in unsigned
        check_alu(10, -10, ALU_SLTU, 1, 0, "SLTU: 10 < -10 (unsigned)"); 
        check_alu(-10, 10, ALU_SLTU, 0, 1, "SLTU: -10 < 10 (unsigned)");

        // --- Resumen del Test ---
        $display("\n-------------------");
        $display("TEST SUMMARY");
        $display("Passed: %0d", tests_passed);
        $display("Failed: %0d", tests_failed);
        $display("-------------------");

        if (tests_failed == 0) begin
            $display("ALL ALU TESTS PASSED SUCCESSFULLY!");
        end else begin
            $display("SOME ALU TESTS FAILED.");
        end

        $finish;
    end

endmodule

tb/waves/alu_waves.vcd
$date
	Tue Jul 29 02:22:22 2025
$end
$version
	Icarus Verilog
$end
$timescale
	1ps
$end
$scope module tb_alu $end
$var wire 1 ! tb_zero $end
$var wire 32 " tb_result [31:0] $end
$var reg 4 # tb_alu_control [3:0] $end
$var reg 32 $ tb_operand1 [31:0] $end
$var reg 32 % tb_operand2 [31:0] $end
$var integer 32 & tests_failed [31:0] $end
$var integer 32 ' tests_passed [31:0] $end
$scope module uut $end
$var wire 4 ( alu_control [3:0] $end
$var wire 32 ) operand1 [31:0] $end
$var wire 32 * operand2 [31:0] $end
$var wire 1 ! zero $end
$var reg 32 + result [31:0] $end
$upscope $end
$scope task check_alu $end
$var reg 4 , ctrl [3:0] $end
$var reg 32 - expected_result [31:0] $end
$var reg 1 . expected_zero $end
$var reg 32 / op1 [31:0] $end
$var reg 32 0 op2 [31:0] $end
$var reg 256 1 test_name [255:0] $end
$upscope $end
$upscope $end
$enddefinitions $end
#0
$dumpvars
b10000010100010001000100001110100010000000110001001100000010000000101011001000000011001000110000 1
b10100 0
b1010 /
0.
b11110 -
b10 ,
b11110 +
b10100 *
b1010 )
b10 (
b0 '
b0 &
b10100 %
b1010 $
b10 #
b11110 "
0!
$end
#1000
1!
b0 "
b0 +
b1 %
b1 *
b11111111111111111111111111111111 $
b11111111111111111111111111111111 )
b100000101000100010001000011101000100000001011010011000100100000001010110010000000110001001000000010100001110100011001010111001101110100011100110010000001111010011001010111001001101111001000000110011001101100011000010110011100101001 1
1.
b0 -
b1 0
b11111111111111111111111111111111 /
b1 '
#2000
0!
b11111111111111111111111111110110 "
b11111111111111111111111111110110 +
b110 #
b110 (
b10100 %
b10100 *
b1010 $
b1010 )
b10100110101010101000010001110100010000000110001001100000010000000101101001000000011001000110000 1
0.
b11111111111111111111111111110110 -
b110 ,
b10100 0
b1010 /
b10 '
#3000
1!
b0 "
b0 +
b110010 %
b110010 *
b110010 $
b110010 )
b10100110101010101000010001110100010000000110101001100000010000000101101001000000011010100110000001000000010100001110100011001010111001101110100011100110010000001111010011001010111001001101111001000000110011001101100011000010110011100101001 1
1.
b0 -
b110010 0
b110010 /
b11 '
#4000
b0 #
b0 (
b1111000011110000111100001111 %
b1111000011110000111100001111 *
b11110000111100001111000011110000 $
b11110000111100001111000011110000 )
b10000010100111001000100 1
b0 ,
b1111000011110000111100001111 0
b11110000111100001111000011110000 /
b100 '
#5000
0!
b11111111111111111111111111111111 "
b11111111111111111111111111111111 +
b1 #
b1 (
b100111101010010 1
0.
b11111111111111111111111111111111 -
b1 ,
b101 '
#6000
b1001 #
b1001 (
b10110000100111101010010 1
b1001 ,
b110 '
#7000
b101000 "
b101000 +
b11 #
b11 (
b10 %
b10 *
b1010 $
b1010 )
b10100110100110001001100001110100010000000110001001100000010000000111100001111000010000000110010 1
b101000 -
b11 ,
b10 0
b1010 /
b111 '
#8000
b111111111111111111111111111101 "
b111111111111111111111111111101 +
b100 #
b100 (
b11111111111111111111111111110110 $
b11111111111111111111111111110110 )
b101001101010010010011000011101000100000001011010011000100110000001000000011111000111110001000000011001000100000001010000110110001101111011001110110100101100011011000010110110000101001 1
b111111111111111111111111111101 -
b100 ,
b11111111111111111111111111110110 /
b1000 '
#9000
b11111111111111111111111111111101 "
b11111111111111111111111111111101 +
b101 #
b101 (
b10100110101001001000001001110100010000000101101001100010011000000100000001111100011111000111110001000000011001000100000001010000110000101110010011010010111010001101000011011010110010101110100011010010110001100101001 1
b11111111111111111111111111111101 -
b101 ,
b1001 '
#10000
b1 "
b1 +
b111 #
b111 (
b10100 %
b10100 *
b1010 $
b1010 )
b10100110100110001010100001110100010000000110001001100000010000000111100001000000011001000110000001000000010100001110011011010010110011101101110011001010110010000101001 1
b1 -
b111 ,
b10100 0
b1010 /
b1010 '
#11000
1!
b0 "
b0 +
b1010 %
b1010 *
b10100 $
b10100 )
b10100110100110001010100001110100010000000110010001100000010000000111100001000000011000100110000001000000010100001110011011010010110011101101110011001010110010000101001 1
1.
b0 -
b1010 0
b10100 /
b1011 '
#12000
0!
b1 "
b1 +
b11111111111111111111111111110110 $
b11111111111111111111111111110110 )
b1010011010011000101010000111010001000000010110100110001001100000010000000111100001000000011000100110000001000000010100001110011011010010110011101101110011001010110010000101001 1
0.
b1 -
b11111111111111111111111111110110 /
b1100 '
#13000
1!
b0 "
b0 +
b11111111111111111111111111110110 %
b11111111111111111111111111110110 *
b1010 $
b1010 )
b1010011010011000101010000111010001000000011000100110000001000000011110000100000001011010011000100110000001000000010100001110011011010010110011101101110011001010110010000101001 1
1.
b0 -
b11111111111111111111111111110110 0
b1010 /
b1101 '
#14000
0!
b1 "
b1 +
b1000 #
b1000 (
b10100 %
b10100 *
b10100110100110001010100010101010011101000100000001100010011000000100000001111000010000000110010001100000010000000101000011101010110111001110011011010010110011101101110011001010110010000101001 1
0.
b1 -
b1000 ,
b10100 0
b1110 '
#15000
1!
b0 "
b0 +
b1010 %
b1010 *
b10100 $
b10100 )
b10100110100110001010100010101010011101000100000001100100011000000100000001111000010000000110001001100000010000000101000011101010110111001110011011010010110011101101110011001010110010000101001 1
1.
b0 -
b1010 0
b10100 /
b1111 '
#16000
0!
b1 "
b1 +
b11111111111111111111111111110110 %
b11111111111111111111111111110110 *
b1010 $
b1010 )
b1010011010011000101010001010101001110100010000000110001001100000010000000111100001000000010110100110001001100000010000000101000011101010110111001110011011010010110011101101110011001010110010000101001 1
0.
b1 -
b11111111111111111111111111110110 0
b1010 /
b10000 '
#17000
1!
b0 "
b0 +
b1010 %
b1010 *
b11111111111111111111111111110110 $
b11111111111111111111111111110110 )
b1010011010011000101010001010101001110100010000000101101001100010011000000100000001111000010000000110001001100000010000000101000011101010110111001110011011010010110011101101110011001010110010000101001 1
1.
b0 -
b1010 0
b11111111111111111111111111110110 /
b10001 '
#18000
b10010 '
